mcp2cli/__init__.py
mcp2cli/main.py
mcp2cli-0.1.3.dist-info/METADATA
mcp2cli-0.1.3.dist-info/WHEEL
mcp2cli-0.1.3.dist-info/entry_points.txt
mcp2cli-0.1.3.dist-info/licenses/LICENSE
mcp2cli-0.1.3.dist-info/RECORD
