Metadata-Version: 2.4
Name: mcp2cli
Version: 0.1.3
Summary: A command-line tool to interact with Model Context Protocol (MCP) servers.
Project-URL: Homepage, https://github.com/PsychArch/mcp2cli
Project-URL: Bug Tracker, https://github.com/PsychArch/mcp2cli/issues
Author-email: PsychArch <psycharch@users.noreply.github.com>
License: Copyright (c) 2025 PsychArch
License-File: LICENSE
Classifier: License :: OSI Approved :: MIT License
Classifier: Operating System :: OS Independent
Classifier: Programming Language :: Python :: 3
Classifier: Programming Language :: Python :: 3.13
Requires-Python: >=3.11
Requires-Dist: fastmcp>=2.10.6
Requires-Dist: mcp[cli]>=1.10.1
Requires-Dist: rich>=14.0.0
Requires-Dist: typer>=0.16.0
